scrapy_streamitem-0.1.0.dist-info/RECORD
scrapy_streamitem-0.1.0.dist-info/WHEEL
scrapy_streamitem-0.1.0.dist-info/metadata.json
scrapy_streamitem-0.1.0.dist-info/DESCRIPTION.rst
scrapy_streamitem-0.1.0.dist-info/METADATA
scrapy_streamitem-0.1.0.dist-info/top_level.txt
streamitem/storages.py
streamitem/loaders.py
streamitem/items.py
streamitem/exporters.py
streamitem/__init__.py
