Metadata-Version: 2.0
Name: scrapy-streamitem
Version: 0.1.0
Summary: Scrapy support for working with streamcorpus Stream Items
Home-page: http://scrapy.org
Author: scrapinghub
Author-email: javier@scrapinghub.com
License: BSD
Platform: UNKNOWN
Classifier: Framework :: Scrapy
Classifier: Development Status :: 5 - Production/Stable
Classifier: Environment :: Console
Classifier: Intended Audience :: Developers
Classifier: License :: OSI Approved :: BSD License
Classifier: Operating System :: OS Independent
Classifier: Programming Language :: Python
Classifier: Programming Language :: Python :: 2
Classifier: Programming Language :: Python :: 2.7
Classifier: Topic :: Internet :: WWW/HTTP
Classifier: Topic :: Software Development :: Libraries :: Application Frameworks
Classifier: Topic :: Software Development :: Libraries :: Python Modules
Requires-Dist: Scrapy (>=0.22.0)
Requires-Dist: streamcorpus
